<annotation>
	<folder>cubes</folder>
	<filename>IMG_9775.JPG</filename>
	<path>C:\Users\vadim\Documents\Personal stuff\Cool bits of code\Tensorflow object detection\training_data\cubes\IMG_9775.JPG</path>
	<source>
		<database>Unknown</database>
	</source>
	<size>
		<width>3024</width>
		<height>4032</height>
		<depth>3</depth>
	</size>
	<segmented>0</segmented>
	<object>
		<name>cube</name>
		<pose>Unspecified</pose>
		<truncated>0</truncated>
		<difficult>0</difficult>
		<bndbox>
			<xmin>1128</xmin>
			<ymin>1003</ymin>
			<xmax>2420</xmax>
			<ymax>2308</ymax>
		</bndbox>
	</object>
</annotation>
